AUTHORS.rst
MANIFEST.in
setup.py
bin/pywls
bin/pywls-play
docs/Makefile
docs/authors.rst
docs/conf.py
docs/contributing.rst
docs/history.rst
docs/index.rst
docs/installation.rst
docs/make.bat
docs/readme.rst
docs/usage.rst
lib/pywls/__init__.py
lib/pywls/release.py
lib/pywls.egg-info/PKG-INFO
lib/pywls.egg-info/SOURCES.txt
lib/pywls.egg-info/dependency_links.txt
lib/pywls.egg-info/requires.txt
lib/pywls.egg-info/top_level.txt
lib/pywls/cli/__init__.py
lib/pywls/cli/adhoc.py
lib/pywls/cli/play.py
lib/pywls/utils/__init__.py
lib/pywls/utils/docopt.py
lib/pywls/utils/schema.py
tests/__init__.py
tests/test_pywls.py